{
  "gitSyncId": "673f75e8a10a6c4f5adf7b51_3b6f1584-c78e-46c9-9fae-1a5b749d696b",
  "id": "Directions_GetGoogleSheetLocations",
  "pluginId": "google-sheets-plugin",
  "pluginType": "SAAS",
  "unpublishedAction": {
    "actionConfiguration": {
      "encodeParamsToggle": true,
      "formData": {
        "command": {
          "data": "FETCH_MANY"
        },
        "entityType": {
          "data": "ROWS"
        },
        "pagination": {
          "data": {
            "limit": "20",
            "offset": "0"
          }
        },
        "projection": {
          "data": []
        },
        "queryFormat": {
          "data": "ROWS"
        },
        "range": {
          "data": ""
        },
        "sheetName": {
          "data": "Sheet1"
        },
        "sheetUrl": {
          "data": "https://docs.google.com/spreadsheets/d/15-3cheoIFwRwzmIs42GO6ux7flqOIdv86kw-ZnlDsJE/edit"
        },
        "smartSubstitution": {
          "data": true
        },
        "sortBy": {
          "data": [
            {
              "column": "",
              "order": "Ascending"
            }
          ]
        },
        "tableHeaderIndex": {
          "data": "1"
        },
        "where": {
          "data": {
            "children": [
              {
                "condition": "LT"
              }
            ],
            "condition": "AND"
          }
        }
      },
      "paginationType": "NONE",
      "timeoutInMillisecond": 10000
    },
    "confirmBeforeExecute": false,
    "datasource": {
      "id": "LocationGoogleSheet",
      "isAutoGenerated": false,
      "name": "LocationGoogleSheet",
      "pluginId": "google-sheets-plugin"
    },
    "dynamicBindingPathList": [],
    "executeOnLoad": true,
    "name": "GetGoogleSheetLocations",
    "pageId": "Directions",
    "userSetOnLoad": false
  }
}